[{"country": "中国", "cityID": "7314", "cityName": "长沙", "airportLatitude": 28.186666, "airportLongitude": 113.221664, "airportShortName": "CSX"}, {"country": "泰国", "cityID": "26166", "cityName": "曼谷", "airportLatitude": 13.9125, "airportLongitude": 100.606667, "airportShortName": "DMK"}, {"country": "泰国", "cityID": "26166", "cityName": "曼谷", "airportLatitude": 13.693358, "airportLongitude": 100.750294, "airportShortName": "BKK"}, {"country": "中国", "cityID": "11306", "cityName": "太原", "airportLatitude": 37.7549292, "airportLongitude": 112.6317269, "airportShortName": "TYN"}, {"country": "中国", "cityID": "23190", "cityName": "香港", "airportLatitude": 22.3127972, "airportLongitude": 113.9299013, "airportShortName": "HKG"}, {"country": "中国", "cityID": "25894", "cityName": "上海", "airportLatitude": 31.142797, "airportLongitude": 121.792367, "airportShortName": "PVG"}, {"country": "中国", "cityID": "25894", "cityName": "上海", "airportLatitude": 31.201338, "airportLongitude": 121.336425, "airportShortName": "SHA"}, {"country": "中国", "cityID": "52351", "cityName": "大理", "airportLatitude": 25.651242, "airportLongitude": 100.318552, "airportShortName": "DLU"}, {"country": "泰国", "cityID": "23911", "cityName": "普吉岛", "airportLatitude": 8.133333333, "airportLongitude": 98.31666667, "airportShortName": "HKT"}, {"country": "中国", "cityID": "30114", "cityName": "福州", "airportLatitude": 25.933333, "airportLongitude": 119.661667, "airportShortName": "FOC"}, {"country": "澳门", "cityID": "15097", "cityName": "澳门", "airportLatitude": 22.23333333, "airportLongitude": 113.5833333, "airportShortName": "MFM"}, {"country": "中国", "cityID": "22530", "cityName": "杭州", "airportLatitude": 30.2354271, "airportLongitude": 120.43778, "airportShortName": "HGH"}, {"country": "台湾", "cityID": "19888", "cityName": "台北", "airportLatitude": 25.07639, "airportLongitude": 121.22389, "airportShortName": "TPE"}, {"country": "日本", "cityID": "25438", "cityName": "冲绳", "airportLatitude": 26.206326, "airportLongitude": 127.646596, "airportShortName": "OKA"}, {"country": "台湾", "cityID": "19888", "cityName": "台北", "airportLatitude": 25.13333333, "airportLongitude": 121.5694444, "airportShortName": "TSA"}, {"country": "韩国", "cityID": "35982", "cityName": "首尔", "airportLatitude": 37.56654, "airportLongitude": 126.97797, "airportShortName": "SEL"}, {"country": "韩国", "cityID": "35982", "cityName": "首尔", "airportLatitude": 37.469075, "airportLongitude": 126.450517, "airportShortName": "ICN"}, {"country": "日本", "cityID": "2121", "cityName": "名古屋", "airportLatitude": 34.859243, "airportLongitude": 136.814654, "airportShortName": "NGO"}, {"country": "韩国", "cityID": "35982", "cityName": "首尔", "airportLatitude": 37.558311, "airportLongitude": 126.790586, "airportShortName": "GMP"}, {"country": "菲律宾", "cityID": "29645", "cityName": "马尼拉", "airportLatitude": 14.51666667, "airportLongitude": 121.0166667, "airportShortName": "MNL"}, {"country": "泰国", "cityID": "47656", "cityName": "拉廊", "airportLatitude": 9.852777778, "airportLongitude": 98.62916667, "airportShortName": "UNN"}, {"country": "马来西亚", "cityID": "4723", "cityName": "吉隆坡", "airportLatitude": 2.745556, "airportLongitude": 101.709722, "airportShortName": "KUL"}, {"country": "中国", "cityID": "43910", "cityName": "贵阳", "airportLatitude": 26.5407206, "airportLongitude": 106.8003644, "airportShortName": "KWE"}, {"country": "中国", "cityID": "48344", "cityName": "三亚", "airportLatitude": 18.3, "airportLongitude": 109.4, "airportShortName": "SYX"}, {"country": "泰国", "cityID": "49531", "cityName": "董里", "airportLatitude": 7.5, "airportLongitude": 99.61666667, "airportShortName": "TST"}, {"country": "中国", "cityID": "3286", "cityName": "北京", "airportLatitude": 40.05, "airportLongitude": 116.5833333, "airportShortName": "PEK"}, {"country": "中国", "cityID": "3286", "cityName": "北京", "airportLatitude": 39.90869, "airportLongitude": 116.39751, "airportShortName": "BJS"}, {"country": "泰国", "cityID": "44862", "cityName": "甲米", "airportLatitude": 8.099117, "airportLongitude": 98.986178, "airportShortName": "KBV"}, {"country": "菲律宾", "cityID": "9998", "cityName": "宿务", "airportLatitude": 10.3094424, "airportLongitude": 123.9777887, "airportShortName": "CEB"}, {"country": "泰国", "cityID": "46436", "cityName": "陶公", "airportLatitude": 6.5206976, "airportLongitude": 101.7508507, "airportShortName": "NAW"}, {"country": "日本", "cityID": "21033", "cityName": "东京", "airportLatitude": 35.70903, "airportLongitude": 139.73199, "airportShortName": "TYO"}, {"country": "日本", "cityID": "21033", "cityName": "东京", "airportLatitude": 35.550388, "airportLongitude": 139.779839, "airportShortName": "HND"}, {"country": "印尼", "cityID": "50485", "cityName": "登巴萨", "airportLatitude": -8.75, "airportLongitude": 115.1666667, "airportShortName": "DPS"}, {"country": "尼泊尔", "cityID": "25800", "cityName": "加德满都", "airportLatitude": 27.71666667, "airportLongitude": 85.35, "airportShortName": "KTM"}, {"country": "中国", "cityID": "16996", "cityName": "石家庄", "airportLatitude": 38.05, "airportLongitude": 114.4666667, "airportShortName": "SJW"}, {"country": "马来西亚", "cityID": "26624", "cityName": "瓜拉丁加奴", "airportLatitude": 5.386111111, "airportLongitude": 103.1077778, "airportShortName": "TGG"}, {"country": "中国", "cityID": "8199", "cityName": "稻城", "airportLatitude": 29.316668, "airportLongitude": 100.060005, "airportShortName": "DCY"}, {"country": "泰国", "cityID": "6042", "cityName": "清迈", "airportLatitude": 18.8, "airportLongitude": 98.96666667, "airportShortName": "CNX"}, {"country": "美国", "cityID": "16078", "cityName": "洛杉矶", "airportLatitude": 33.94336, "airportLongitude": -118.40856, "airportShortName": "LAX"}, {"country": "日本", "cityID": "25901", "cityName": "大阪", "airportLatitude": 34.66975, "airportLongitude": 135.49713, "airportShortName": "OSA"}, {"country": "日本", "cityID": "25901", "cityName": "大阪", "airportLatitude": 34.432021, "airportLongitude": 135.230281, "airportShortName": "KIX"}, {"country": "中国", "cityID": "52371", "cityName": "张家界", "airportLatitude": 29.13333333, "airportLongitude": 110.4833333, "airportShortName": "DYG"}, {"country": "马来西亚", "cityID": "28359", "cityName": "亚庇", "airportLatitude": 5.933333333, "airportLongitude": 116.05, "airportShortName": "BKI"}, {"country": "意大利", "cityID": "25465", "cityName": "罗马", "airportLatitude": 41.79972222, "airportLongitude": 12.23416667, "airportShortName": "FCO"}, {"country": "意大利", "cityID": "25465", "cityName": "罗马", "airportLatitude": 41.90278, "airportLongitude": 12.49637, "airportShortName": "ROM"}, {"country": "中国", "cityID": "20379", "cityName": "拉萨", "airportLatitude": 29.2909579, "airportLongitude": 90.901786, "airportShortName": "LXA"}, {"country": "越南", "cityID": "52164", "cityName": "Cam Ranh", "airportLatitude": 11.998056, "airportLongitude": 109.219444, "airportShortName": "CXR"}, {"country": "俄罗斯", "cityID": "14713", "cityName": "莫斯科", "airportLatitude": 55.96944444, "airportLongitude": 37.41666667, "airportShortName": "SVO"}, {"country": "俄罗斯", "cityID": "14713", "cityName": "莫斯科", "airportLatitude": 55.75407, "airportLongitude": 37.62037, "airportShortName": "MOW"}, {"country": "马来西亚", "cityID": "4414", "cityName": "斗湖", "airportLatitude": 4.314305, "airportLongitude": 118.115019, "airportShortName": "TWU"}, {"country": "中国", "cityID": "9466", "cityName": "苏州", "airportLatitude": 31.3, "airportLongitude": 120.633, "airportShortName": "SZV"}, {"country": "菲律宾", "cityID": "1242", "cityName": "巴科洛德", "airportLatitude": 10.63333333, "airportLongitude": 122.9333333, "airportShortName": "BCD"}, {"country": "英国", "cityID": "28501", "cityName": "伦敦", "airportLatitude": 51.50735, "airportLongitude": -0.12766, "airportShortName": "LON"}, {"country": "英国", "cityID": "28501", "cityName": "伦敦", "airportLatitude": 51.46666667, "airportLongitude": -0.45, "airportShortName": "LHR"}, {"country": "德国", "cityID": "14057", "cityName": "慕尼黑", "airportLatitude": 48.35, "airportLongitude": 11.78333333, "airportShortName": "MUC"}, {"country": "新西兰", "cityID": "21341", "cityName": "惠灵顿", "airportLatitude": -41.33333333, "airportLongitude": 174.8, "airportShortName": "WLG"}, {"country": "美国", "cityID": "15830", "cityName": "纽约", "airportLatitude": 40.76666667, "airportLongitude": -73.86666667, "airportShortName": "LGA"}, {"country": "西班牙", "cityID": "32213", "cityName": "马德里", "airportLatitude": 40.46666667, "airportLongitude": -3.566666667, "airportShortName": "MAD"}, {"country": "中国", "cityID": "55046", "cityName": "乌海", "airportLatitude": 39.794724, "airportLongitude": 106.799164, "airportShortName": "WUA"}, {"country": "新西兰", "cityID": "19171", "cityName": "布伦海姆", "airportLatitude": -41.53333333, "airportLongitude": 173.9166667, "airportShortName": "BHE"}, {"country": "德国", "cityID": "9109", "cityName": "柏林", "airportLatitude": 52.56666667, "airportLongitude": 13.3, "airportShortName": "TXL"}, {"country": "德国", "cityID": "9109", "cityName": "柏林", "airportLatitude": 52.52083, "airportLongitude": 13.40941, "airportShortName": "BER"}, {"country": "津巴布韦", "cityID": "23306", "cityName": "Harare", "airportLatitude": -17.9326707, "airportLongitude": 31.0916519, "airportShortName": "HRE"}, {"country": "美国", "cityID": "13852", "cityName": "旧金山", "airportLatitude": 37.61666667, "airportLongitude": -122.3833333, "airportShortName": "SFO"}, {"country": "澳大利亚", "cityID": "2258", "cityName": "悉尼", "airportLatitude": -33.93333333, "airportLongitude": 151.1666667, "airportShortName": "SYD"}, {"country": "冰岛", "cityID": "11024", "cityName": "雷克雅未克", "airportLatitude": 64.13622, "airportLongitude": -21.89472, "airportShortName": "REK"}, {"country": "冰岛", "cityID": "11024", "cityName": "雷克雅未克", "airportLatitude": 63.98333333, "airportLongitude": -22.6, "airportShortName": "KEF"}, {"country": "格鲁吉亚", "cityID": "24544", "cityName": "第比利斯", "airportLatitude": 41.75, "airportLongitude": 44.75, "airportShortName": "TBS"}, {"country": "肯尼亚", "cityID": "26243", "cityName": "内罗毕", "airportLatitude": -1.316666667, "airportLongitude": 36.93333333, "airportShortName": "NBO"}, {"country": "美国", "cityID": "7054", "cityName": "西雅图", "airportLatitude": 47.45, "airportLongitude": -122.3, "airportShortName": "SEA"}, {"country": "俄罗斯", "cityID": "14713", "cityName": "莫斯科", "airportLatitude": 55.58333333, "airportLongitude": 37.26666667, "airportShortName": "VKO"}, {"country": "中国", "cityID": "14422", "cityName": "西林吉", "airportLatitude": 52.91639, "airportLongitude": 122.42222, "airportShortName": "OHE"}, {"country": "俄罗斯", "cityID": "14713", "cityName": "莫斯科", "airportLatitude": 55.4, "airportLongitude": 37.88333333, "airportShortName": "DME"}, {"country": "美国", "cityID": "15830", "cityName": "纽约", "airportLatitude": 40.63333333, "airportLongitude": -73.78333333, "airportShortName": "JFK"}, {"country": "美国", "cityID": "15830", "cityName": "纽约", "airportLatitude": 40.75096, "airportLongitude": -73.98741, "airportShortName": "NYC"}, {"country": "加拿大", "cityID": "6966", "cityName": "Montreal", "airportLatitude": 45.46666667, "airportLongitude": -73.75277778, "airportShortName": "YUL"}, {"country": "加拿大", "cityID": "6966", "cityName": "Montreal", "airportLatitude": 45.5, "airportLongitude": -73.583, "airportShortName": "YMQ"}, {"country": "美国", "cityID": "7505", "cityName": "奥马哈", "airportLatitude": 41.3, "airportLongitude": -95.9, "airportShortName": "OMA"}, {"country": "以色列", "cityID": "54749", "cityName": "特拉维夫", "airportLatitude": 31.98333333, "airportLongitude": 34.88333333, "airportShortName": "TLV"}, {"country": "美国", "cityID": "13189", "cityName": "圣安娜", "airportLatitude": 33.66666667, "airportLongitude": -117.8666667, "airportShortName": "SNA"}, {"country": "德国", "cityID": "9109", "cityName": "柏林", "airportLatitude": 52.3789047, "airportLongitude": 13.5172565, "airportShortName": "SXF"}, {"country": "法国", "cityID": "36014", "cityName": "巴黎", "airportLatitude": 49.01666667, "airportLongitude": 2.55, "airportShortName": "CDG"}, {"country": "法国", "cityID": "36014", "cityName": "巴黎", "airportLatitude": 48.85749, "airportLongitude": 2.3473, "airportShortName": "PAR"}, {"country": "美国", "cityID": "28070", "cityName": "檀香山", "airportLatitude": 21.33333333, "airportLongitude": -157.9333333, "airportShortName": "HNL"}, {"country": "美国", "cityID": "8252", "cityName": "纽瓦克", "airportLatitude": 40.68333333, "airportLongitude": -74.16666667, "airportShortName": "EWR"}, {"country": "美国", "cityID": "19830", "cityName": "安大略", "airportLatitude": 34.05, "airportLongitude": -117.6166667, "airportShortName": "ONT"}, {"country": "乌克兰", "cityID": "15139", "cityName": "基辅", "airportLatitude": 50.411945, "airportLongitude": 30.443054, "airportShortName": "IEV"}, {"country": "乌克兰", "cityID": "60978", "cityName": "Boryspil’", "airportLatitude": 50.35, "airportLongitude": 30.916666, "airportShortName": "KBP"}, {"country": "斐济", "cityID": "46400", "cityName": "南迪", "airportLatitude": -17.75, "airportLongitude": 177.45, "airportShortName": "NAN"}, {"country": "英国", "cityID": "28501", "cityName": "伦敦", "airportLatitude": 51.51666667, "airportLongitude": 0.06666666667, "airportShortName": "LCY"}, {"country": "英国", "cityID": "28501", "cityName": "伦敦", "airportLatitude": 51.15, "airportLongitude": -0.1833333333, "airportShortName": "LGW"}, {"country": "美国", "cityID": "25588", "cityName": "波士顿", "airportLatitude": 42.369325, "airportLongitude": -71.014767, "airportShortName": "BOS"}, {"country": "克罗地亚", "cityID": "24952", "cityName": "杜布罗夫尼克", "airportLatitude": 42.56666667, "airportLongitude": 18.26666667, "airportShortName": "DBV"}, {"country": "英国", "cityID": "23746", "cityName": "南安普敦", "airportLatitude": 50.95, "airportLongitude": -1.35, "airportShortName": "SOU"}, {"country": "尼日利亚", "cityID": "25271", "cityName": "拉戈", "airportLatitude": 6.5666, "airportLongitude": 3.3166, "airportShortName": "LOS"}, {"country": "以色列", "cityID": "53959", "cityName": "奥瓦达", "airportLatitude": 31.0, "airportLongitude": 34.48333333, "airportShortName": "VDA"}, {"country": "越南", "cityID": "42707", "cityName": "Dalat", "airportLatitude": 11.75, "airportLongitude": 108.3666667, "airportShortName": "DLI"}, {"country": "日本", "cityID": "25901", "cityName": "大阪", "airportLatitude": 34.789536, "airportLongitude": 135.438089, "airportShortName": "ITM"}, {"country": "中国", "cityID": "17708", "cityName": "广州", "airportLatitude": 23.3925, "airportLongitude": 113.298889, "airportShortName": "CAN"}, {"country": "菲律宾", "cityID": "9998", "cityName": "宿务", "airportLatitude": 10.3094424, "airportLongitude": 123.9777887, "airportShortName": "CEB"}, {"country": "中国", "cityID": "34301", "cityName": "郑州", "airportLatitude": 34.5251398, "airportLongitude": 113.8462032, "airportShortName": "CGO"}, {"country": "中国", "cityID": "7314", "cityName": "长沙", "airportLatitude": 28.186666, "airportLongitude": 113.221664, "airportShortName": "CSX"}, {"country": "越南", "cityID": "52164", "cityName": "Cam Ranh", "airportLatitude": 11.998056, "airportLongitude": 109.219444, "airportShortName": "CXR"}, {"country": "中国", "cityID": "42234", "cityName": "常州", "airportLatitude": 31.912637, "airportLongitude": 119.783717, "airportShortName": "CZX"}, {"country": "中国", "cityID": "8199", "cityName": "稻城", "airportLatitude": 29.316668, "airportLongitude": 100.060005, "airportShortName": "DCY"}, {"country": "中国", "cityID": "2251", "cityName": "大连", "airportLatitude": 38.96666667, "airportLongitude": 121.55, "airportShortName": "DLC"}, {"country": "中国", "cityID": "43955", "cityName": "海口", "airportLatitude": 19.941387, "airportLongitude": 110.452774, "airportShortName": "HAK"}, {"country": "中国", "cityID": "10161", "cityName": "合肥", "airportLatitude": 31.98599, "airportLongitude": 116.96915, "airportShortName": "HFE"}, {"country": "中国", "cityID": "22530", "cityName": "杭州", "airportLatitude": 30.2354271, "airportLongitude": 120.43778, "airportShortName": "HGH"}, {"country": "泰国", "cityID": "23911", "cityName": "普吉岛", "airportLatitude": 8.133333333, "airportLongitude": 98.31666667, "airportShortName": "HKT"}, {"country": "中国", "cityID": "32344", "cityName": "银川", "airportLatitude": 38.322434, "airportLongitude": 106.388282, "airportShortName": "INC"}, {"country": "泰国", "cityID": "44862", "cityName": "甲米", "airportLatitude": 8.099117, "airportLongitude": 98.986178, "airportShortName": "KBV"}, {"country": "中国", "cityID": "27614", "cityName": "康定", "airportLatitude": 30.1575, "airportLongitude": 101.734722, "airportShortName": "KGT"}, {"country": "中国", "cityID": "46420", "cityName": "南昌", "airportLatitude": 28.8568135, "airportLongitude": 115.912045, "airportShortName": "KHN"}, {"country": "菲律宾", "cityID": "13471", "cityName": "卡利博", "airportLatitude": 11.7, "airportLongitude": 122.3666667, "airportShortName": "KLO"}, {"country": "中国", "cityID": "30991", "cityName": "昆明", "airportLatitude": 25.101944, "airportLongitude": 102.929167, "airportShortName": "KMG"}, {"country": "中国", "cityID": "18698", "cityName": "兰州", "airportLatitude": 36.01666667, "airportLongitude": 103.75, "airportShortName": "LHW"}, {"country": "中国", "cityID": "53304", "cityName": "丽江", "airportLatitude": 26.67242, "airportLongitude": 100.24592, "airportShortName": "LJG"}, {"country": "中国", "cityID": "20379", "cityName": "拉萨", "airportLatitude": 29.2909579, "airportLongitude": 90.901786, "airportShortName": "LXA"}, {"country": "中国", "cityID": "72367", "cityName": "林芝", "airportLatitude": 29.303333, "airportLongitude": 94.335278, "airportShortName": "LZY"}, {"country": "中国", "cityID": "24286", "cityName": "宁波", "airportLatitude": 29.817548, "airportLongitude": 121.466702, "airportShortName": "NGB"}, {"country": "中国", "cityID": "20564", "cityName": "南京", "airportLatitude": 31.733612, "airportLongitude": 118.871666, "airportShortName": "NKG"}, {"country": "中国", "cityID": "19750", "cityName": "南宁", "airportLatitude": 22.6073205, "airportLongitude": 108.1720919, "airportShortName": "NNG"}, {"country": "中国", "cityID": "3286", "cityName": "北京", "airportLatitude": 40.05, "airportLongitude": 116.5833333, "airportShortName": "PEK"}, {"country": "中国", "cityID": "25894", "cityName": "上海", "airportLatitude": 31.142797, "airportLongitude": 121.792367, "airportShortName": "PVG"}, {"country": "中国", "cityID": "53990", "cityName": "攀枝花", "airportLatitude": 26.542314, "airportLongitude": 101.798519, "airportShortName": "PZI"}, {"country": "中国", "cityID": "16996", "cityName": "石家庄", "airportLatitude": 38.05, "airportLongitude": 114.4666667, "airportShortName": "SJW"}, {"country": "中国", "cityID": "33762", "cityName": "汕头", "airportLatitude": 23.427199, "airportLongitude": 116.7641264, "airportShortName": "SWA"}, {"country": "澳大利亚", "cityID": "2258", "cityName": "悉尼", "airportLatitude": -33.93333333, "airportLongitude": 151.1666667, "airportShortName": "SYD"}, {"country": "中国", "cityID": "48344", "cityName": "三亚", "airportLatitude": 18.3, "airportLongitude": 109.4, "airportShortName": "SYX"}, {"country": "中国", "cityID": "9007", "cityName": "深圳", "airportLatitude": 22.55, "airportLongitude": 113.9166667, "airportShortName": "SZX"}, {"country": "中国", "cityID": "13023", "cityName": "青岛", "airportLatitude": 36.26264, "airportLongitude": 120.385509, "airportShortName": "TAO"}, {"country": "中国", "cityID": "36184", "cityName": "济南", "airportLatitude": 36.8519177, "airportLongitude": 117.2183956, "airportShortName": "TNA"}, {"country": "台湾", "cityID": "19888", "cityName": "台北", "airportLatitude": 25.13333333, "airportLongitude": 121.5694444, "airportShortName": "TSA"}, {"country": "中国", "cityID": "21998", "cityName": "天津", "airportLatitude": 39.1244729, "airportLongitude": 117.3468366, "airportShortName": "TSN"}, {"country": "中国", "cityID": "11306", "cityName": "太原", "airportLatitude": 37.7549292, "airportLongitude": 112.6317269, "airportShortName": "TYN"}, {"country": "中国", "cityID": "4316", "cityName": "乌鲁木齐", "airportLatitude": 43.905, "airportLongitude": 87.476406, "airportShortName": "URC"}, {"country": "中国", "cityID": "28481", "cityName": "武汉", "airportLatitude": 30.5, "airportLongitude": 114.3333333, "airportShortName": "WUH"}, {"country": "中国", "cityID": "12046", "cityName": "无锡", "airportLatitude": 31.4907671, "airportLongitude": 120.4291785, "airportShortName": "WUX"}, {"country": "中国", "cityID": "35600", "cityName": "西安", "airportLatitude": 34.44482, "airportLongitude": 108.755808, "airportShortName": "XIY"}, {"country": "中国", "cityID": "21424", "cityName": "西宁", "airportLatitude": 36.524723, "airportLongitude": 102.03889, "airportShortName": "XNN"}, {"country": "中国", "cityID": "23231", "cityName": "烟台", "airportLatitude": 37.401667, "airportLongitude": 121.371667, "airportShortName": "YNT"}, {"country": "中国", "cityID": "69820", "cityName": "中卫", "airportLatitude": 37.572778, "airportLongitude": 105.154444, "airportShortName": "ZHY"}, {"country": "中国", "cityID": "55063", "cityName": "徐州", "airportLatitude": 34.26666667, "airportLongitude": 117.1833333, "airportShortName": "XUZ"}, {"country": "日本", "cityID": "25901", "cityName": "大阪", "airportLatitude": 34.432021, "airportLongitude": 135.230281, "airportShortName": "KIX"}, {"country": "中国", "cityID": "4760", "cityName": "洛阳", "airportLatitude": 34.68333333, "airportLongitude": 112.4666667, "airportShortName": "LYA"}, {"country": "中国", "cityID": "25894", "cityName": "上海", "airportLatitude": 31.201338, "airportLongitude": 121.336425, "airportShortName": "SHA"}, {"country": "芬兰", "cityID": "7232", "cityName": "赫尔辛基", "airportLatitude": 60.3193825, "airportLongitude": 24.9412048, "airportShortName": "HEL"}, {"country": "台湾", "cityID": "19888", "cityName": "台北", "airportLatitude": 25.07639, "airportLongitude": 121.22389, "airportShortName": "TPE"}, {"country": "中国", "cityID": "51687", "cityName": "阿克苏", "airportLatitude": 41.17099, "airportLongitude": 80.198196, "airportShortName": "AKU"}, {"country": "泰国", "cityID": "6042", "cityName": "清迈", "airportLatitude": 18.8, "airportLongitude": 98.96666667, "airportShortName": "CNX"}, {"country": "中国", "cityID": "52351", "cityName": "大理", "airportLatitude": 25.651242, "airportLongitude": 100.318552, "airportShortName": "DLU"}, {"country": "阿联酋", "cityID": "6080", "cityName": "迪拜", "airportLatitude": 25.25, "airportLongitude": 55.33333333, "airportShortName": "DXB"}, {"country": "中国", "cityID": "30114", "cityName": "福州", "airportLatitude": 25.933333, "airportLongitude": 119.661667, "airportShortName": "FOC"}, {"country": "中国", "cityID": "61116", "cityName": "淮安", "airportLatitude": 33.777222, "airportLongitude": 119.147778, "airportShortName": "HIA"}, {"country": "中国", "cityID": "23190", "cityName": "香港", "airportLatitude": 22.3127972, "airportLongitude": 113.9299013, "airportShortName": "HKG"}, {"country": "中国", "cityID": "6281", "cityName": "哈尔滨", "airportLatitude": 45.6207614, "airportLongitude": 126.2423814, "airportShortName": "HRB"}, {"country": "韩国", "cityID": "35982", "cityName": "首尔", "airportLatitude": 37.469075, "airportLongitude": 126.450517, "airportShortName": "ICN"}, {"country": "中国", "cityID": "316102", "cityName": "六盘水", "airportLatitude": 26.608612, "airportLongitude": 104.97833, "airportShortName": "LPF"}, {"country": "中国", "cityID": "259", "cityName": "连云港", "airportLatitude": 34.572595, "airportLongitude": 118.876395, "airportShortName": "LYG"}, {"country": "澳门", "cityID": "15097", "cityName": "澳门", "airportLatitude": 22.23333333, "airportLongitude": 113.5833333, "airportShortName": "MFM"}, {"country": "中国", "cityID": "11214", "cityName": "温州", "airportLatitude": 27.9114589, "airportLongitude": 120.8530216, "airportShortName": "WNZ"}, {"country": "中国", "cityID": "34115", "cityName": "厦门", "airportLatitude": 24.534445, "airportLongitude": 118.13167, "airportShortName": "XMN"}, {"country": "中国", "cityID": "24949", "cityName": "运城", "airportLatitude": 35.116389, "airportLongitude": 111.033333, "airportShortName": "YCU"}, {"country": "中国", "cityID": "55070", "cityName": "盐城", "airportLatitude": 33.386471, "airportLongitude": 120.206001, "airportShortName": "YNZ"}, {"country": "中国", "cityID": "23871", "cityName": "珠海", "airportLatitude": 22.01666667, "airportLongitude": 113.3333333, "airportShortName": "ZUH"}, {"country": "台湾", "cityID": "33504", "cityName": "高雄市", "airportLatitude": 22.58333333, "airportLongitude": 120.4166667, "airportShortName": "KHH"}, {"country": "中国", "cityID": "6617", "cityName": "北海", "airportLatitude": 21.5382791, "airportLongitude": 109.292101, "airportShortName": "BHY"}, {"country": "中国", "cityID": "4398", "cityName": "长春", "airportLatitude": 43.906666, "airportLongitude": 125.201385, "airportShortName": "CGQ"}, {"country": "中国", "cityID": "7490", "cityName": "景洪", "airportLatitude": 22.01666667, "airportLongitude": 100.8, "airportShortName": "JHG"}, {"country": "中国", "cityID": "43910", "cityName": "贵阳", "airportLatitude": 26.5407206, "airportLongitude": 106.8003644, "airportShortName": "KWE"}, {"country": "中国", "cityID": "1955", "cityName": "桂林", "airportLatitude": 25.18333333, "airportLongitude": 110.15, "airportShortName": "KWL"}, {"country": "中国", "cityID": "11981", "cityName": "沈阳", "airportLatitude": 41.81666667, "airportLongitude": 123.5, "airportShortName": "SHE"}, {"country": "中国", "cityID": "28337", "cityName": "腾越（腾冲）", "airportLatitude": 24.991389, "airportLongitude": 98.495833, "airportShortName": "TCZ"}, {"country": "中国", "cityID": "55092", "cityName": "义乌", "airportLatitude": 29.3415103, "airportLongitude": 120.0341387, "airportShortName": "YIW"}, {"country": "马来西亚", "cityID": "4723", "cityName": "吉隆坡", "airportLatitude": 2.745556, "airportLongitude": 101.709722, "airportShortName": "KUL"}, {"country": "中国", "cityID": "307616", "cityName": "德宏", "airportLatitude": 24.40204, "airportLongitude": 98.53233, "airportShortName": "LUM"}, {"country": "泰国", "cityID": "26166", "cityName": "曼谷", "airportLatitude": 13.9125, "airportLongitude": 100.606667, "airportShortName": "DMK"}, {"country": "中国", "cityID": "56389", "cityName": "黄山", "airportLatitude": 29.73333333, "airportLongitude": 118.3, "airportShortName": "TXN"}, {"country": "中国", "cityID": "55062", "cityName": "兴义", "airportLatitude": 25.0882, "airportLongitude": 104.9587, "airportShortName": "ACX"}, {"country": "中国", "cityID": "2129", "cityName": "百色", "airportLatitude": 23.720001, "airportLongitude": 106.96027, "airportShortName": "AEB"}, {"country": "中国", "cityID": "28076", "cityName": "毕节", "airportLatitude": 27.3002001, "airportLongitude": 105.3014936, "airportShortName": "BFJ"}, {"country": "中国", "cityID": "14874", "cityName": "长治", "airportLatitude": 36.18333333, "airportLongitude": 113.1333333, "airportShortName": "CIH"}, {"country": "中国", "cityID": "58034", "cityName": "鄂尔多斯", "airportLatitude": 39.85, "airportLongitude": 110.0333333, "airportShortName": "DSN"}, {"country": "中国", "cityID": "98808", "cityName": "固原", "airportLatitude": 36.076111, "airportLongitude": 106.218056, "airportShortName": "GYU"}, {"country": "中国", "cityID": "301589", "cityName": "邯郸", "airportLatitude": 36.525833, "airportLongitude": 114.424995, "airportShortName": "HDG"}, {"country": "中国", "cityID": "29808", "cityName": "Zhongduo", "airportLatitude": 29.5175, "airportLongitude": 108.829167, "airportShortName": "JIQ"}, {"country": "中国", "cityID": "34729", "cityName": "济宁", "airportLatitude": 35.292778, "airportLongitude": 116.346107, "airportShortName": "JNG"}, {"country": "中国", "cityID": "17023", "cityName": "零陵", "airportLatitude": 26.233, "airportLongitude": 111.617, "airportShortName": "LLF"}, {"country": "中国", "cityID": "91755", "cityName": "吕梁", "airportLatitude": 37.68139, "airportLongitude": 111.142494, "airportShortName": "LLV"}, {"country": "中国", "cityID": "19015", "cityName": "柳州", "airportLatitude": 24.277222, "airportLongitude": 109.385277, "airportShortName": "LZH"}, {"country": "中国", "cityID": "53562", "cityName": "梅州", "airportLatitude": 24.35, "airportLongitude": 116.1333333, "airportShortName": "MXZ"}, {"country": "中国", "cityID": "54523", "cityName": "普洱", "airportLatitude": 22.83333333, "airportLongitude": 101.0, "airportShortName": "SYM"}, {"country": "中国", "cityID": "54825", "cityName": "铜仁", "airportLatitude": 27.88295, "airportLongitude": 109.303802, "airportShortName": "TEN"}, {"country": "中国", "cityID": "29504", "cityName": "天水", "airportLatitude": 34.559723, "airportLongitude": 105.86, "airportShortName": "THQ"}, {"country": "中国", "cityID": "87473", "cityName": "乌兰察布", "airportLatitude": 41.1245858, "airportLongitude": 113.094519, "airportShortName": "UCB"}, {"country": "中国", "cityID": "303439", "cityName": "榆林", "airportLatitude": 38.267222, "airportLongitude": 109.731389, "airportShortName": "UYN"}, {"country": "中国", "cityID": "76867", "cityName": "十堰", "airportLatitude": 32.591013, "airportLongitude": 110.908672, "airportShortName": "WDS"}, {"country": "新西兰", "cityID": "54998", "cityName": "Waitangi", "airportLatitude": -35.16666667, "airportLongitude": 173.9666667, "airportShortName": "WGN"}, {"country": "中国", "cityID": "55055", "cityName": "襄阳", "airportLatitude": 32.1492487, "airportLongitude": 112.2929932, "airportShortName": "XFN"}, {"country": "中国", "cityID": "21784", "cityName": "湛江", "airportLatitude": 21.21178, "airportLongitude": 110.363, "airportShortName": "ZHA"}, {"country": "中国", "cityID": "17024", "cityName": "张家口", "airportLatitude": 40.739166, "airportLongitude": 114.93083, "airportShortName": "ZQZ"}, {"country": "新西兰", "cityID": "2575", "cityName": "奥克兰", "airportLatitude": -37.00477, "airportLongitude": 174.78267, "airportShortName": "AKL"}, {"country": "中国", "cityID": "44217", "cityName": "呼和浩特", "airportLatitude": 40.851665, "airportLongitude": 111.824448, "airportShortName": "HET"}, {"country": "英国", "cityID": "28501", "cityName": "伦敦", "airportLatitude": 51.15, "airportLongitude": -0.1833333333, "airportShortName": "LGW"}, {"country": "澳大利亚", "cityID": "13998", "cityName": "墨尔本", "airportLatitude": -37.661667, "airportLongitude": 144.83333, "airportShortName": "MEL"}, {"country": "俄罗斯", "cityID": "14713", "cityName": "莫斯科", "airportLatitude": 55.96944444, "airportLongitude": 37.41666667, "airportShortName": "SVO"}, {"country": "中国", "cityID": "55069", "cityName": "延安", "airportLatitude": 36.6384258, "airportLongitude": 109.5573004, "airportShortName": "ENY"}, {"country": "意大利", "cityID": "25465", "cityName": "罗马", "airportLatitude": 41.79972222, "airportLongitude": 12.23416667, "airportShortName": "FCO"}, {"country": "美国", "cityID": "15830", "cityName": "纽约", "airportLatitude": 40.63333333, "airportLongitude": -73.78333333, "airportShortName": "JFK"}, {"country": "美国", "cityID": "16078", "cityName": "洛杉矶", "airportLatitude": 33.94336, "airportLongitude": -118.40856, "airportShortName": "LAX"}, {"country": "日本", "cityID": "21033", "cityName": "东京", "airportLatitude": 35.771969, "airportLongitude": 140.392764, "airportShortName": "NRT"}, {"country": "印尼", "cityID": "50485", "cityName": "登巴萨", "airportLatitude": -8.75, "airportLongitude": 115.1666667, "airportShortName": "DPS"}, {"country": "中国", "cityID": "18862", "cityName": "保山", "airportLatitude": 25.0512656, "airportLongitude": 99.1654192, "airportShortName": "BSD"}, {"country": "中国", "cityID": "55311", "cityName": "台州", "airportLatitude": 28.55672, "airportLongitude": 121.42225, "airportShortName": "HYN"}, {"country": "中国", "cityID": "6395", "cityName": "南通", "airportLatitude": 32.067, "airportLongitude": 120.967, "airportShortName": "NTG"}, {"country": "中国", "cityID": "6337", "cityName": "泉州", "airportLatitude": 24.9, "airportLongitude": 118.5833333, "airportShortName": "JJN"}, {"country": "中国", "cityID": "19945", "cityName": "张掖", "airportLatitude": 25.82235, "airportLongitude": 114.9067, "airportShortName": "KOW"}, {"country": "中国", "cityID": "17489", "cityName": "西昌", "airportLatitude": 27.96666667, "airportLongitude": 102.2166667, "airportShortName": "XIC"}, {"country": "新加坡", "cityID": "20828", "cityName": "新加坡", "airportLatitude": 1.3620863, "airportLongitude": 103.9906911, "airportShortName": "SIN"}, {"country": "中国", "cityID": "22610", "cityName": "昭通", "airportLatitude": 27.31666667, "airportLongitude": 103.8, "airportShortName": "ZAT"}, {"country": "中国", "cityID": "52411", "cityName": "香格里拉", "airportLatitude": 27.79318, "airportLongitude": 99.68181, "airportShortName": "DIG"}, {"country": "越南", "cityID": "34211", "cityName": "河内", "airportLatitude": 21.2188504, "airportLongitude": 105.8033395, "airportShortName": "HAN"}, {"country": "中国", "cityID": "52748", "cityName": "衡阳", "airportLatitude": 26.9, "airportLongitude": 112.6, "airportShortName": "HNY"}, {"country": "中国", "cityID": "44308", "cityName": "惠州", "airportLatitude": 23.083, "airportLongitude": 114.367, "airportShortName": "HUZ"}, {"country": "中国", "cityID": "9089", "cityName": "临沂", "airportLatitude": 35.05, "airportLongitude": 118.333, "airportShortName": "LYI"}, {"country": "泰国", "cityID": "56280", "cityName": "苏梅岛", "airportLatitude": 9.55, "airportLongitude": 100.0666667, "airportShortName": "USM"}, {"country": "中国", "cityID": "28708", "cityName": "库尔勒", "airportLatitude": 41.73333333, "airportLongitude": 86.15, "airportShortName": "KRL"}, {"country": "中国", "cityID": "316074", "cityName": "文山", "airportLatitude": 23.375555, "airportLongitude": 104.24305, "airportShortName": "WNH"}, {"country": "卡塔尔", "cityID": "15839", "cityName": "多哈", "airportLatitude": 25.2609842, "airportLongitude": 51.613737, "airportShortName": "DOH"}, {"country": "柬埔寨", "cityID": "10892", "cityName": "金边", "airportLatitude": 11.55, "airportLongitude": 104.85, "airportShortName": "PNH"}, {"country": "柬埔寨", "cityID": "32645", "cityName": "暹粒", "airportLatitude": 13.41666667, "airportLongitude": 103.8166667, "airportShortName": "REP"}, {"country": "泰国", "cityID": "26166", "cityName": "曼谷", "airportLatitude": 13.693358, "airportLongitude": 100.750294, "airportShortName": "BKK"}, {"country": "中国", "cityID": "51922", "cityName": "昌都", "airportLatitude": 30.54978, "airportLongitude": 97.10651, "airportShortName": "BPX"}, {"country": "中国", "cityID": "30961", "cityName": "重庆", "airportLatitude": 29.7174947, "airportLongitude": 106.6370176, "airportShortName": "CKG"}]